imagingcontrol4pyside6/__init__.py
imagingcontrol4pyside6/__init__.pyi
imagingcontrol4pyside6/imagingcontrol4pyside6lib.so
imagingcontrol4pyside6/py.typed
imagingcontrol4pyside6/qt6-dialogs-dyn.so
imagingcontrol4pyside6-6.9.0.102.dist-info/METADATA
imagingcontrol4pyside6-6.9.0.102.dist-info/WHEEL
imagingcontrol4pyside6-6.9.0.102.dist-info/RECORD
