Metadata-Version: 2.4
Name: imagingcontrol4pyside6
Version: 6.9.0.102
Summary: IC Imaging Control 4 PySide6 Dialogs
Author: The Imaging Source
Author-email: support@theimagingsource.com
License: IC Imaging Control License Agreement
Keywords: PySide6,SDK,camera,dialog,gui,ic4,imagingcontrol,the imaging source
Classifier: Development Status :: 5 - Production/Stable
Classifier: Intended Audience :: Developers
Classifier: Intended Audience :: Information Technology
Classifier: Intended Audience :: Manufacturing
Classifier: Intended Audience :: Other Audience
Classifier: Intended Audience :: Science/Research
Classifier: License :: Other/Proprietary License
Classifier: Operating System :: Microsoft :: Windows
Classifier: Operating System :: POSIX :: Linux
Classifier: Programming Language :: Python :: 3
Classifier: Topic :: Multimedia :: Graphics :: Capture
Classifier: Topic :: Multimedia :: Graphics :: Capture :: Digital Camera
Classifier: Topic :: Multimedia :: Video :: Capture
Classifier: Topic :: Scientific/Engineering :: Image Processing
Classifier: Topic :: Software Development
Classifier: Topic :: Software Development :: Libraries
Requires-Python: <3.14,>=3.10
Requires-Dist: imagingcontrol4>=1.0.0
Requires-Dist: pyside6<6.10,>=6.9.0
